pyindicators/__init__.py
pyindicators/date_range.py
pyindicators/exceptions.py
pyindicators/indicators/__init__.py
pyindicators/indicators/adx.py
pyindicators/indicators/average_true_range.py
pyindicators/indicators/bollinger_bands.py
pyindicators/indicators/commodity_channel_index.py
pyindicators/indicators/crossover.py
pyindicators/indicators/crossunder.py
pyindicators/indicators/divergence.py
pyindicators/indicators/exponential_moving_average.py
pyindicators/indicators/is_down_trend.py
pyindicators/indicators/is_up_trend.py
pyindicators/indicators/macd.py
pyindicators/indicators/rate_of_change.py
pyindicators/indicators/rsi.py
pyindicators/indicators/simple_moving_average.py
pyindicators/indicators/stochastic_oscillator.py
pyindicators/indicators/up_and_down_trends.py
pyindicators/indicators/utils.py
pyindicators/indicators/weighted_moving_average.py
pyindicators/indicators/williams_percent_range.py
pyindicators-0.15.2.dist-info/LICENSE
pyindicators-0.15.2.dist-info/METADATA
pyindicators-0.15.2.dist-info/WHEEL
pyindicators-0.15.2.dist-info/RECORD
