Metadata-Version: 2.1
Name: pyindicators
Version: 0.15.2
Summary: PyIndicators is a powerful and user-friendly Python library for technical analysis indicators and metrics. Written entirely in Python, it requires no external dependencies, ensuring seamless integration and ease of use.
Author: Marc van Duyn
Requires-Python: >=3.10
Classifier: Programming Language :: Python :: 3
Classifier: Programming Language :: Python :: 3.10
Classifier: Programming Language :: Python :: 3.11
Classifier: Programming Language :: Python :: 3.12
Requires-Dist: numpy (>=1.26.4)
Requires-Dist: pandas (>=2.0.0)
Requires-Dist: polars (>=1.0.0)
Requires-Dist: pyarrow (>=12.0.0)
Requires-Dist: scipy (>=1.15.1)
